{
  "content": [
    {
      "type": "paragraph",
      "children": [
        {
          "text": ""
        }
      ]
    },
    {
      "type": "event",
      "uuid": "07584d24-7ab1-465c-80d5-ddbe627d522e",
      "includes": [
        "media",
        "annotations",
        "description"
      ],
      "children": [
        {
          "text": ""
        }
      ]
    },
    {
      "type": "paragraph",
      "children": [
        {
          "text": ""
        }
      ]
    }
  ],
  "created_at": "2025-10-21T23:29:50.348Z",
  "created_by": "raymondhyser",
  "title": "Episode 273: Venezuela Elections with Professor Kurt Weyland",
  "slug": "episode-273-venezuela-elections-with-profess",
  "updated_at": "2026-02-11T17:20:43.136Z",
  "updated_by": "raymondhyser",
  "autogenerate": {
    "enabled": true,
    "type": "event",
    "type_id": "07584d24-7ab1-465c-80d5-ddbe627d522e"
  }
}